<!--
	- I/O mapping
	- Version: 
	- Date: Tue Aug  8 16:59:10 2023
-->

<io_mapping>
	<io name="gfpga_pad_QL_PREIO_A2F[2244:2244]" net="clock0" dir="input"/>
	<io name="gfpga_pad_QL_PREIO_A2F[2168:2168]" net="reset" dir="input"/>
	<io name="gfpga_pad_QL_PREIO_A2F[973:973]" net="lr" dir="input"/>
	<io name="gfpga_pad_QL_PREIO_A2F[1989:1989]" net="loopback_en" dir="input"/>
	<io name="gfpga_pad_QL_PREIO_A2F[1969:1969]" net="counter_in[199]" dir="input"/>
	<io name="gfpga_pad_QL_PREIO_A2F[2006:2006]" net="counter_in[198]" dir="input"/>
	<io name="gfpga_pad_QL_PREIO_A2F[286:286]" net="counter_in[197]" dir="input"/>
	<io name="gfpga_pad_QL_PREIO_A2F[1803:1803]" net="counter_in[196]" dir="input"/>
	<io name="gfpga_pad_QL_PREIO_A2F[1841:1841]" net="counter_in[195]" dir="input"/>
	<io name="gfpga_pad_QL_PREIO_A2F[1482:1482]" net="counter_in[194]" dir="input"/>
	<io name="gfpga_pad_QL_PREIO_A2F[1836:1836]" net="counter_in[193]" dir="input"/>
	<io name="gfpga_pad_QL_PREIO_A2F[794:794]" net="counter_in[192]" dir="input"/>
	<io name="gfpga_pad_QL_PREIO_A2F[2299:2299]" net="counter_in[191]" dir="input"/>
	<io name="gfpga_pad_QL_PREIO_A2F[810:810]" net="counter_in[190]" dir="input"/>
	<io name="gfpga_pad_QL_PREIO_A2F[872:872]" net="counter_in[189]" dir="input"/>
	<io name="gfpga_pad_QL_PREIO_A2F[1421:1421]" net="counter_in[188]" dir="input"/>
	<io name="gfpga_pad_QL_PREIO_A2F[817:817]" net="counter_in[187]" dir="input"/>
	<io name="gfpga_pad_QL_PREIO_A2F[1980:1980]" net="counter_in[186]" dir="input"/>
	<io name="gfpga_pad_QL_PREIO_A2F[2033:2033]" net="counter_in[185]" dir="input"/>
	<io name="gfpga_pad_QL_PREIO_A2F[1412:1412]" net="counter_in[184]" dir="input"/>
	<io name="gfpga_pad_QL_PREIO_A2F[1794:1794]" net="counter_in[183]" dir="input"/>
	<io name="gfpga_pad_QL_PREIO_A2F[1850:1850]" net="counter_in[182]" dir="input"/>
	<io name="gfpga_pad_QL_PREIO_A2F[1753:1753]" net="counter_in[181]" dir="input"/>
	<io name="gfpga_pad_QL_PREIO_A2F[1398:1398]" net="counter_in[180]" dir="input"/>
	<io name="gfpga_pad_QL_PREIO_A2F[2290:2290]" net="counter_in[179]" dir="input"/>
	<io name="gfpga_pad_QL_PREIO_A2F[2205:2205]" net="counter_in[178]" dir="input"/>
	<io name="gfpga_pad_QL_PREIO_A2F[2252:2252]" net="counter_in[177]" dir="input"/>
	<io name="gfpga_pad_QL_PREIO_A2F[2085:2085]" net="counter_in[176]" dir="input"/>
	<io name="gfpga_pad_QL_PREIO_A2F[2274:2274]" net="counter_in[175]" dir="input"/>
	<io name="gfpga_pad_QL_PREIO_A2F[728:728]" net="counter_in[174]" dir="input"/>
	<io name="gfpga_pad_QL_PREIO_A2F[1751:1751]" net="counter_in[173]" dir="input"/>
	<io name="gfpga_pad_QL_PREIO_A2F[316:316]" net="counter_in[172]" dir="input"/>
	<io name="gfpga_pad_QL_PREIO_A2F[1817:1817]" net="counter_in[171]" dir="input"/>
	<io name="gfpga_pad_QL_PREIO_A2F[1025:1025]" net="counter_in[170]" dir="input"/>
	<io name="gfpga_pad_QL_PREIO_A2F[1039:1039]" net="counter_in[169]" dir="input"/>
	<io name="gfpga_pad_QL_PREIO_A2F[1840:1840]" net="counter_in[168]" dir="input"/>
	<io name="gfpga_pad_QL_PREIO_A2F[1073:1073]" net="counter_in[167]" dir="input"/>
	<io name="gfpga_pad_QL_PREIO_A2F[2124:2124]" net="counter_in[166]" dir="input"/>
	<io name="gfpga_pad_QL_PREIO_A2F[2008:2008]" net="counter_in[165]" dir="input"/>
	<io name="gfpga_pad_QL_PREIO_A2F[2190:2190]" net="counter_in[164]" dir="input"/>
	<io name="gfpga_pad_QL_PREIO_A2F[1968:1968]" net="counter_in[163]" dir="input"/>
	<io name="gfpga_pad_QL_PREIO_A2F[1847:1847]" net="counter_in[162]" dir="input"/>
	<io name="gfpga_pad_QL_PREIO_A2F[930:930]" net="counter_in[161]" dir="input"/>
	<io name="gfpga_pad_QL_PREIO_A2F[1983:1983]" net="counter_in[160]" dir="input"/>
	<io name="gfpga_pad_QL_PREIO_A2F[1952:1952]" net="counter_in[159]" dir="input"/>
	<io name="gfpga_pad_QL_PREIO_A2F[1985:1985]" net="counter_in[158]" dir="input"/>
	<io name="gfpga_pad_QL_PREIO_A2F[1019:1019]" net="counter_in[157]" dir="input"/>
	<io name="gfpga_pad_QL_PREIO_A2F[1971:1971]" net="counter_in[156]" dir="input"/>
	<io name="gfpga_pad_QL_PREIO_A2F[2028:2028]" net="counter_in[155]" dir="input"/>
	<io name="gfpga_pad_QL_PREIO_A2F[1510:1510]" net="counter_in[154]" dir="input"/>
	<io name="gfpga_pad_QL_PREIO_A2F[1942:1942]" net="counter_in[153]" dir="input"/>
	<io name="gfpga_pad_QL_PREIO_A2F[710:710]" net="counter_in[152]" dir="input"/>
	<io name="gfpga_pad_QL_PREIO_A2F[1439:1439]" net="counter_in[151]" dir="input"/>
	<io name="gfpga_pad_QL_PREIO_A2F[2243:2243]" net="counter_in[150]" dir="input"/>
	<io name="gfpga_pad_QL_PREIO_A2F[2267:2267]" net="counter_in[149]" dir="input"/>
	<io name="gfpga_pad_QL_PREIO_A2F[2039:2039]" net="counter_in[148]" dir="input"/>
	<io name="gfpga_pad_QL_PREIO_A2F[719:719]" net="counter_in[147]" dir="input"/>
	<io name="gfpga_pad_QL_PREIO_A2F[2083:2083]" net="counter_in[146]" dir="input"/>
	<io name="gfpga_pad_QL_PREIO_A2F[1829:1829]" net="counter_in[145]" dir="input"/>
	<io name="gfpga_pad_QL_PREIO_A2F[1935:1935]" net="counter_in[144]" dir="input"/>
	<io name="gfpga_pad_QL_PREIO_A2F[1922:1922]" net="counter_in[143]" dir="input"/>
	<io name="gfpga_pad_QL_PREIO_A2F[2295:2295]" net="counter_in[142]" dir="input"/>
	<io name="gfpga_pad_QL_PREIO_A2F[2014:2014]" net="counter_in[141]" dir="input"/>
	<io name="gfpga_pad_QL_PREIO_A2F[1913:1913]" net="counter_in[140]" dir="input"/>
	<io name="gfpga_pad_QL_PREIO_A2F[279:279]" net="counter_in[139]" dir="input"/>
	<io name="gfpga_pad_QL_PREIO_A2F[2069:2069]" net="counter_in[138]" dir="input"/>
	<io name="gfpga_pad_QL_PREIO_A2F[1949:1949]" net="counter_in[137]" dir="input"/>
	<io name="gfpga_pad_QL_PREIO_A2F[1394:1394]" net="counter_in[136]" dir="input"/>
	<io name="gfpga_pad_QL_PREIO_A2F[1791:1791]" net="counter_in[135]" dir="input"/>
	<io name="gfpga_pad_QL_PREIO_A2F[1869:1869]" net="counter_in[134]" dir="input"/>
	<io name="gfpga_pad_QL_PREIO_A2F[2191:2191]" net="counter_in[133]" dir="input"/>
	<io name="gfpga_pad_QL_PREIO_A2F[2087:2087]" net="counter_in[132]" dir="input"/>
	<io name="gfpga_pad_QL_PREIO_A2F[2193:2193]" net="counter_in[131]" dir="input"/>
	<io name="gfpga_pad_QL_PREIO_A2F[2207:2207]" net="counter_in[130]" dir="input"/>
	<io name="gfpga_pad_QL_PREIO_A2F[329:329]" net="counter_in[129]" dir="input"/>
	<io name="gfpga_pad_QL_PREIO_A2F[2224:2224]" net="counter_in[128]" dir="input"/>
	<io name="gfpga_pad_QL_PREIO_A2F[2213:2213]" net="counter_in[127]" dir="input"/>
	<io name="gfpga_pad_QL_PREIO_A2F[1441:1441]" net="counter_in[126]" dir="input"/>
	<io name="gfpga_pad_QL_PREIO_A2F[671:671]" net="counter_in[125]" dir="input"/>
	<io name="gfpga_pad_QL_PREIO_A2F[147:147]" net="counter_in[124]" dir="input"/>
	<io name="gfpga_pad_QL_PREIO_A2F[1866:1866]" net="counter_in[123]" dir="input"/>
	<io name="gfpga_pad_QL_PREIO_A2F[712:712]" net="counter_in[122]" dir="input"/>
	<io name="gfpga_pad_QL_PREIO_A2F[2210:2210]" net="counter_in[121]" dir="input"/>
	<io name="gfpga_pad_QL_PREIO_A2F[2055:2055]" net="counter_in[120]" dir="input"/>
	<io name="gfpga_pad_QL_PREIO_A2F[1066:1066]" net="counter_in[119]" dir="input"/>
	<io name="gfpga_pad_QL_PREIO_A2F[678:678]" net="counter_in[118]" dir="input"/>
	<io name="gfpga_pad_QL_PREIO_A2F[1777:1777]" net="counter_in[117]" dir="input"/>
	<io name="gfpga_pad_QL_PREIO_A2F[2020:2020]" net="counter_in[116]" dir="input"/>
	<io name="gfpga_pad_QL_PREIO_A2F[858:858]" net="counter_in[115]" dir="input"/>
	<io name="gfpga_pad_QL_PREIO_A2F[1954:1954]" net="counter_in[114]" dir="input"/>
	<io name="gfpga_pad_QL_PREIO_A2F[2123:2123]" net="counter_in[113]" dir="input"/>
	<io name="gfpga_pad_QL_PREIO_A2F[1957:1957]" net="counter_in[112]" dir="input"/>
	<io name="gfpga_pad_QL_PREIO_A2F[686:686]" net="counter_in[111]" dir="input"/>
	<io name="gfpga_pad_QL_PREIO_A2F[795:795]" net="counter_in[110]" dir="input"/>
	<io name="gfpga_pad_QL_PREIO_A2F[677:677]" net="counter_in[109]" dir="input"/>
	<io name="gfpga_pad_QL_PREIO_A2F[1951:1951]" net="counter_in[108]" dir="input"/>
	<io name="gfpga_pad_QL_PREIO_A2F[2112:2112]" net="counter_in[107]" dir="input"/>
	<io name="gfpga_pad_QL_PREIO_A2F[230:230]" net="counter_in[106]" dir="input"/>
	<io name="gfpga_pad_QL_PREIO_A2F[697:697]" net="counter_in[105]" dir="input"/>
	<io name="gfpga_pad_QL_PREIO_A2F[2021:2021]" net="counter_in[104]" dir="input"/>
	<io name="gfpga_pad_QL_PREIO_A2F[1761:1761]" net="counter_in[103]" dir="input"/>
	<io name="gfpga_pad_QL_PREIO_A2F[304:304]" net="counter_in[102]" dir="input"/>
	<io name="gfpga_pad_QL_PREIO_A2F[882:882]" net="counter_in[101]" dir="input"/>
	<io name="gfpga_pad_QL_PREIO_A2F[1953:1953]" net="counter_in[100]" dir="input"/>
	<io name="gfpga_pad_QL_PREIO_A2F[1795:1795]" net="counter_in[99]" dir="input"/>
	<io name="gfpga_pad_QL_PREIO_A2F[718:718]" net="counter_in[98]" dir="input"/>
	<io name="gfpga_pad_QL_PREIO_A2F[2018:2018]" net="counter_in[97]" dir="input"/>
	<io name="gfpga_pad_QL_PREIO_A2F[2167:2167]" net="counter_in[96]" dir="input"/>
	<io name="gfpga_pad_QL_PREIO_A2F[900:900]" net="counter_in[95]" dir="input"/>
	<io name="gfpga_pad_QL_PREIO_A2F[2025:2025]" net="counter_in[94]" dir="input"/>
	<io name="gfpga_pad_QL_PREIO_A2F[2289:2289]" net="counter_in[93]" dir="input"/>
	<io name="gfpga_pad_QL_PREIO_A2F[1419:1419]" net="counter_in[92]" dir="input"/>
	<io name="gfpga_pad_QL_PREIO_A2F[1916:1916]" net="counter_in[91]" dir="input"/>
	<io name="gfpga_pad_QL_PREIO_A2F[845:845]" net="counter_in[90]" dir="input"/>
	<io name="gfpga_pad_QL_PREIO_A2F[904:904]" net="counter_in[89]" dir="input"/>
	<io name="gfpga_pad_QL_PREIO_A2F[2194:2194]" net="counter_in[88]" dir="input"/>
	<io name="gfpga_pad_QL_PREIO_A2F[2199:2199]" net="counter_in[87]" dir="input"/>
	<io name="gfpga_pad_QL_PREIO_A2F[793:793]" net="counter_in[86]" dir="input"/>
	<io name="gfpga_pad_QL_PREIO_A2F[1036:1036]" net="counter_in[85]" dir="input"/>
	<io name="gfpga_pad_QL_PREIO_A2F[934:934]" net="counter_in[84]" dir="input"/>
	<io name="gfpga_pad_QL_PREIO_A2F[922:922]" net="counter_in[83]" dir="input"/>
	<io name="gfpga_pad_QL_PREIO_A2F[1401:1401]" net="counter_in[82]" dir="input"/>
	<io name="gfpga_pad_QL_PREIO_A2F[792:792]" net="counter_in[81]" dir="input"/>
	<io name="gfpga_pad_QL_PREIO_A2F[1731:1731]" net="counter_in[80]" dir="input"/>
	<io name="gfpga_pad_QL_PREIO_A2F[910:910]" net="counter_in[79]" dir="input"/>
	<io name="gfpga_pad_QL_PREIO_A2F[1048:1048]" net="counter_in[78]" dir="input"/>
	<io name="gfpga_pad_QL_PREIO_A2F[775:775]" net="counter_in[77]" dir="input"/>
	<io name="gfpga_pad_QL_PREIO_A2F[1390:1390]" net="counter_in[76]" dir="input"/>
	<io name="gfpga_pad_QL_PREIO_A2F[1998:1998]" net="counter_in[75]" dir="input"/>
	<io name="gfpga_pad_QL_PREIO_A2F[1075:1075]" net="counter_in[74]" dir="input"/>
	<io name="gfpga_pad_QL_PREIO_A2F[2054:2054]" net="counter_in[73]" dir="input"/>
	<io name="gfpga_pad_QL_PREIO_A2F[2000:2000]" net="counter_in[72]" dir="input"/>
	<io name="gfpga_pad_QL_PREIO_A2F[1402:1402]" net="counter_in[71]" dir="input"/>
	<io name="gfpga_pad_QL_PREIO_A2F[1462:1462]" net="counter_in[70]" dir="input"/>
	<io name="gfpga_pad_QL_PREIO_A2F[2218:2218]" net="counter_in[69]" dir="input"/>
	<io name="gfpga_pad_QL_PREIO_A2F[766:766]" net="counter_in[68]" dir="input"/>
	<io name="gfpga_pad_QL_PREIO_A2F[2003:2003]" net="counter_in[67]" dir="input"/>
	<io name="gfpga_pad_QL_PREIO_A2F[1385:1385]" net="counter_in[66]" dir="input"/>
	<io name="gfpga_pad_QL_PREIO_A2F[1420:1420]" net="counter_in[65]" dir="input"/>
	<io name="gfpga_pad_QL_PREIO_A2F[1429:1429]" net="counter_in[64]" dir="input"/>
	<io name="gfpga_pad_QL_PREIO_A2F[875:875]" net="counter_in[63]" dir="input"/>
	<io name="gfpga_pad_QL_PREIO_A2F[1370:1370]" net="counter_in[62]" dir="input"/>
	<io name="gfpga_pad_QL_PREIO_A2F[1779:1779]" net="counter_in[61]" dir="input"/>
	<io name="gfpga_pad_QL_PREIO_A2F[2047:2047]" net="counter_in[60]" dir="input"/>
	<io name="gfpga_pad_QL_PREIO_A2F[1435:1435]" net="counter_in[59]" dir="input"/>
	<io name="gfpga_pad_QL_PREIO_A2F[825:825]" net="counter_in[58]" dir="input"/>
	<io name="gfpga_pad_QL_PREIO_A2F[846:846]" net="counter_in[57]" dir="input"/>
	<io name="gfpga_pad_QL_PREIO_A2F[660:660]" net="counter_in[56]" dir="input"/>
	<io name="gfpga_pad_QL_PREIO_A2F[1958:1958]" net="counter_in[55]" dir="input"/>
	<io name="gfpga_pad_QL_PREIO_A2F[175:175]" net="counter_in[54]" dir="input"/>
	<io name="gfpga_pad_QL_PREIO_A2F[2105:2105]" net="counter_in[53]" dir="input"/>
	<io name="gfpga_pad_QL_PREIO_A2F[1940:1940]" net="counter_in[52]" dir="input"/>
	<io name="gfpga_pad_QL_PREIO_A2F[2247:2247]" net="counter_in[51]" dir="input"/>
	<io name="gfpga_pad_QL_PREIO_A2F[1975:1975]" net="counter_in[50]" dir="input"/>
	<io name="gfpga_pad_QL_PREIO_A2F[1069:1069]" net="counter_in[49]" dir="input"/>
	<io name="gfpga_pad_QL_PREIO_A2F[1956:1956]" net="counter_in[48]" dir="input"/>
	<io name="gfpga_pad_QL_PREIO_A2F[2010:2010]" net="counter_in[47]" dir="input"/>
	<io name="gfpga_pad_QL_PREIO_A2F[1944:1944]" net="counter_in[46]" dir="input"/>
	<io name="gfpga_pad_QL_PREIO_A2F[715:715]" net="counter_in[45]" dir="input"/>
	<io name="gfpga_pad_QL_PREIO_A2F[829:829]" net="counter_in[44]" dir="input"/>
	<io name="gfpga_pad_QL_PREIO_A2F[1422:1422]" net="counter_in[43]" dir="input"/>
	<io name="gfpga_pad_QL_PREIO_A2F[1372:1372]" net="counter_in[42]" dir="input"/>
	<io name="gfpga_pad_QL_PREIO_A2F[219:219]" net="counter_in[41]" dir="input"/>
	<io name="gfpga_pad_QL_PREIO_A2F[1057:1057]" net="counter_in[40]" dir="input"/>
	<io name="gfpga_pad_QL_PREIO_A2F[1964:1964]" net="counter_in[39]" dir="input"/>
	<io name="gfpga_pad_QL_PREIO_A2F[2073:2073]" net="counter_in[38]" dir="input"/>
	<io name="gfpga_pad_QL_PREIO_A2F[2088:2088]" net="counter_in[37]" dir="input"/>
	<io name="gfpga_pad_QL_PREIO_A2F[1948:1948]" net="counter_in[36]" dir="input"/>
	<io name="gfpga_pad_QL_PREIO_A2F[843:843]" net="counter_in[35]" dir="input"/>
	<io name="gfpga_pad_QL_PREIO_A2F[826:826]" net="counter_in[34]" dir="input"/>
	<io name="gfpga_pad_QL_PREIO_A2F[1407:1407]" net="counter_in[33]" dir="input"/>
	<io name="gfpga_pad_QL_PREIO_A2F[2082:2082]" net="counter_in[32]" dir="input"/>
	<io name="gfpga_pad_QL_PREIO_A2F[2214:2214]" net="counter_in[31]" dir="input"/>
	<io name="gfpga_pad_QL_PREIO_A2F[352:352]" net="counter_in[30]" dir="input"/>
	<io name="gfpga_pad_QL_PREIO_A2F[865:865]" net="counter_in[29]" dir="input"/>
	<io name="gfpga_pad_QL_PREIO_A2F[1963:1963]" net="counter_in[28]" dir="input"/>
	<io name="gfpga_pad_QL_PREIO_A2F[2066:2066]" net="counter_in[27]" dir="input"/>
	<io name="gfpga_pad_QL_PREIO_A2F[263:263]" net="counter_in[26]" dir="input"/>
	<io name="gfpga_pad_QL_PREIO_A2F[2081:2081]" net="counter_in[25]" dir="input"/>
	<io name="gfpga_pad_QL_PREIO_A2F[1387:1387]" net="counter_in[24]" dir="input"/>
	<io name="gfpga_pad_QL_PREIO_A2F[2220:2220]" net="counter_in[23]" dir="input"/>
	<io name="gfpga_pad_QL_PREIO_A2F[2031:2031]" net="counter_in[22]" dir="input"/>
	<io name="gfpga_pad_QL_PREIO_A2F[1996:1996]" net="counter_in[21]" dir="input"/>
	<io name="gfpga_pad_QL_PREIO_A2F[2212:2212]" net="counter_in[20]" dir="input"/>
	<io name="gfpga_pad_QL_PREIO_A2F[1384:1384]" net="counter_in[19]" dir="input"/>
	<io name="gfpga_pad_QL_PREIO_A2F[1994:1994]" net="counter_in[18]" dir="input"/>
	<io name="gfpga_pad_QL_PREIO_A2F[165:165]" net="counter_in[17]" dir="input"/>
	<io name="gfpga_pad_QL_PREIO_A2F[1759:1759]" net="counter_in[16]" dir="input"/>
	<io name="gfpga_pad_QL_PREIO_A2F[1861:1861]" net="counter_in[15]" dir="input"/>
	<io name="gfpga_pad_QL_PREIO_A2F[1773:1773]" net="counter_in[14]" dir="input"/>
	<io name="gfpga_pad_QL_PREIO_A2F[1923:1923]" net="counter_in[13]" dir="input"/>
	<io name="gfpga_pad_QL_PREIO_A2F[2037:2037]" net="counter_in[12]" dir="input"/>
	<io name="gfpga_pad_QL_PREIO_A2F[716:716]" net="counter_in[11]" dir="input"/>
	<io name="gfpga_pad_QL_PREIO_A2F[1848:1848]" net="counter_in[10]" dir="input"/>
	<io name="gfpga_pad_QL_PREIO_A2F[1319:1319]" net="counter_in[9]" dir="input"/>
	<io name="gfpga_pad_QL_PREIO_A2F[1986:1986]" net="counter_in[8]" dir="input"/>
	<io name="gfpga_pad_QL_PREIO_A2F[831:831]" net="counter_in[7]" dir="input"/>
	<io name="gfpga_pad_QL_PREIO_A2F[293:293]" net="counter_in[6]" dir="input"/>
	<io name="gfpga_pad_QL_PREIO_A2F[2051:2051]" net="counter_in[5]" dir="input"/>
	<io name="gfpga_pad_QL_PREIO_A2F[2177:2177]" net="counter_in[4]" dir="input"/>
	<io name="gfpga_pad_QL_PREIO_A2F[1987:1987]" net="counter_in[3]" dir="input"/>
	<io name="gfpga_pad_QL_PREIO_A2F[1424:1424]" net="counter_in[2]" dir="input"/>
	<io name="gfpga_pad_QL_PREIO_A2F[337:337]" net="counter_in[1]" dir="input"/>
	<io name="gfpga_pad_QL_PREIO_A2F[1391:1391]" net="counter_in[0]" dir="input"/>
	<io name="gfpga_pad_QL_PREIO_F2A[895:895]" net="loopback_error" dir="output"/>
	<io name="gfpga_pad_QL_PREIO_F2A[1897:1897]" net="out[199]" dir="output"/>
	<io name="gfpga_pad_QL_PREIO_F2A[1879:1879]" net="out[198]" dir="output"/>
	<io name="gfpga_pad_QL_PREIO_F2A[1917:1917]" net="out[197]" dir="output"/>
	<io name="gfpga_pad_QL_PREIO_F2A[1828:1828]" net="out[196]" dir="output"/>
	<io name="gfpga_pad_QL_PREIO_F2A[1809:1809]" net="out[195]" dir="output"/>
	<io name="gfpga_pad_QL_PREIO_F2A[1467:1467]" net="out[194]" dir="output"/>
	<io name="gfpga_pad_QL_PREIO_F2A[1881:1881]" net="out[193]" dir="output"/>
	<io name="gfpga_pad_QL_PREIO_F2A[1020:1020]" net="out[192]" dir="output"/>
	<io name="gfpga_pad_QL_PREIO_F2A[2196:2196]" net="out[191]" dir="output"/>
	<io name="gfpga_pad_QL_PREIO_F2A[808:808]" net="out[190]" dir="output"/>
	<io name="gfpga_pad_QL_PREIO_F2A[2015:2015]" net="out[189]" dir="output"/>
	<io name="gfpga_pad_QL_PREIO_F2A[217:217]" net="out[188]" dir="output"/>
	<io name="gfpga_pad_QL_PREIO_F2A[926:926]" net="out[187]" dir="output"/>
	<io name="gfpga_pad_QL_PREIO_F2A[1981:1981]" net="out[186]" dir="output"/>
	<io name="gfpga_pad_QL_PREIO_F2A[1926:1926]" net="out[185]" dir="output"/>
	<io name="gfpga_pad_QL_PREIO_F2A[1579:1579]" net="out[184]" dir="output"/>
	<io name="gfpga_pad_QL_PREIO_F2A[1506:1506]" net="out[183]" dir="output"/>
	<io name="gfpga_pad_QL_PREIO_F2A[1733:1733]" net="out[182]" dir="output"/>
	<io name="gfpga_pad_QL_PREIO_F2A[1797:1797]" net="out[181]" dir="output"/>
	<io name="gfpga_pad_QL_PREIO_F2A[1547:1547]" net="out[180]" dir="output"/>
	<io name="gfpga_pad_QL_PREIO_F2A[1636:1636]" net="out[179]" dir="output"/>
	<io name="gfpga_pad_QL_PREIO_F2A[1475:1475]" net="out[178]" dir="output"/>
	<io name="gfpga_pad_QL_PREIO_F2A[1854:1854]" net="out[177]" dir="output"/>
	<io name="gfpga_pad_QL_PREIO_F2A[1492:1492]" net="out[176]" dir="output"/>
	<io name="gfpga_pad_QL_PREIO_F2A[1929:1929]" net="out[175]" dir="output"/>
	<io name="gfpga_pad_QL_PREIO_F2A[1446:1446]" net="out[174]" dir="output"/>
	<io name="gfpga_pad_QL_PREIO_F2A[1586:1586]" net="out[173]" dir="output"/>
	<io name="gfpga_pad_QL_PREIO_F2A[1484:1484]" net="out[172]" dir="output"/>
	<io name="gfpga_pad_QL_PREIO_F2A[1653:1653]" net="out[171]" dir="output"/>
	<io name="gfpga_pad_QL_PREIO_F2A[1801:1801]" net="out[170]" dir="output"/>
	<io name="gfpga_pad_QL_PREIO_F2A[1478:1478]" net="out[169]" dir="output"/>
	<io name="gfpga_pad_QL_PREIO_F2A[1654:1654]" net="out[168]" dir="output"/>
	<io name="gfpga_pad_QL_PREIO_F2A[1126:1126]" net="out[167]" dir="output"/>
	<io name="gfpga_pad_QL_PREIO_F2A[1864:1864]" net="out[166]" dir="output"/>
	<io name="gfpga_pad_QL_PREIO_F2A[1844:1844]" net="out[165]" dir="output"/>
	<io name="gfpga_pad_QL_PREIO_F2A[1893:1893]" net="out[164]" dir="output"/>
	<io name="gfpga_pad_QL_PREIO_F2A[1901:1901]" net="out[163]" dir="output"/>
	<io name="gfpga_pad_QL_PREIO_F2A[1804:1804]" net="out[162]" dir="output"/>
	<io name="gfpga_pad_QL_PREIO_F2A[1832:1832]" net="out[161]" dir="output"/>
	<io name="gfpga_pad_QL_PREIO_F2A[1979:1979]" net="out[160]" dir="output"/>
	<io name="gfpga_pad_QL_PREIO_F2A[1827:1827]" net="out[159]" dir="output"/>
	<io name="gfpga_pad_QL_PREIO_F2A[1855:1855]" net="out[158]" dir="output"/>
	<io name="gfpga_pad_QL_PREIO_F2A[1860:1860]" net="out[157]" dir="output"/>
	<io name="gfpga_pad_QL_PREIO_F2A[1911:1911]" net="out[156]" dir="output"/>
	<io name="gfpga_pad_QL_PREIO_F2A[1853:1853]" net="out[155]" dir="output"/>
	<io name="gfpga_pad_QL_PREIO_F2A[1529:1529]" net="out[154]" dir="output"/>
	<io name="gfpga_pad_QL_PREIO_F2A[1992:1992]" net="out[153]" dir="output"/>
	<io name="gfpga_pad_QL_PREIO_F2A[1865:1865]" net="out[152]" dir="output"/>
	<io name="gfpga_pad_QL_PREIO_F2A[2023:2023]" net="out[151]" dir="output"/>
	<io name="gfpga_pad_QL_PREIO_F2A[2187:2187]" net="out[150]" dir="output"/>
	<io name="gfpga_pad_QL_PREIO_F2A[2106:2106]" net="out[149]" dir="output"/>
	<io name="gfpga_pad_QL_PREIO_F2A[2042:2042]" net="out[148]" dir="output"/>
	<io name="gfpga_pad_QL_PREIO_F2A[2221:2221]" net="out[147]" dir="output"/>
	<io name="gfpga_pad_QL_PREIO_F2A[2034:2034]" net="out[146]" dir="output"/>
	<io name="gfpga_pad_QL_PREIO_F2A[1993:1993]" net="out[145]" dir="output"/>
	<io name="gfpga_pad_QL_PREIO_F2A[1936:1936]" net="out[144]" dir="output"/>
	<io name="gfpga_pad_QL_PREIO_F2A[2080:2080]" net="out[143]" dir="output"/>
	<io name="gfpga_pad_QL_PREIO_F2A[2102:2102]" net="out[142]" dir="output"/>
	<io name="gfpga_pad_QL_PREIO_F2A[2057:2057]" net="out[141]" dir="output"/>
	<io name="gfpga_pad_QL_PREIO_F2A[2077:2077]" net="out[140]" dir="output"/>
	<io name="gfpga_pad_QL_PREIO_F2A[2136:2136]" net="out[139]" dir="output"/>
	<io name="gfpga_pad_QL_PREIO_F2A[2062:2062]" net="out[138]" dir="output"/>
	<io name="gfpga_pad_QL_PREIO_F2A[2119:2119]" net="out[137]" dir="output"/>
	<io name="gfpga_pad_QL_PREIO_F2A[1977:1977]" net="out[136]" dir="output"/>
	<io name="gfpga_pad_QL_PREIO_F2A[2089:2089]" net="out[135]" dir="output"/>
	<io name="gfpga_pad_QL_PREIO_F2A[2170:2170]" net="out[134]" dir="output"/>
	<io name="gfpga_pad_QL_PREIO_F2A[2231:2231]" net="out[133]" dir="output"/>
	<io name="gfpga_pad_QL_PREIO_F2A[2241:2241]" net="out[132]" dir="output"/>
	<io name="gfpga_pad_QL_PREIO_F2A[190:190]" net="out[131]" dir="output"/>
	<io name="gfpga_pad_QL_PREIO_F2A[2201:2201]" net="out[130]" dir="output"/>
	<io name="gfpga_pad_QL_PREIO_F2A[270:270]" net="out[129]" dir="output"/>
	<io name="gfpga_pad_QL_PREIO_F2A[214:214]" net="out[128]" dir="output"/>
	<io name="gfpga_pad_QL_PREIO_F2A[149:149]" net="out[127]" dir="output"/>
	<io name="gfpga_pad_QL_PREIO_F2A[252:252]" net="out[126]" dir="output"/>
	<io name="gfpga_pad_QL_PREIO_F2A[648:648]" net="out[125]" dir="output"/>
	<io name="gfpga_pad_QL_PREIO_F2A[233:233]" net="out[124]" dir="output"/>
	<io name="gfpga_pad_QL_PREIO_F2A[2242:2242]" net="out[123]" dir="output"/>
	<io name="gfpga_pad_QL_PREIO_F2A[264:264]" net="out[122]" dir="output"/>
	<io name="gfpga_pad_QL_PREIO_F2A[148:148]" net="out[121]" dir="output"/>
	<io name="gfpga_pad_QL_PREIO_F2A[2164:2164]" net="out[120]" dir="output"/>
	<io name="gfpga_pad_QL_PREIO_F2A[661:661]" net="out[119]" dir="output"/>
	<io name="gfpga_pad_QL_PREIO_F2A[436:436]" net="out[118]" dir="output"/>
	<io name="gfpga_pad_QL_PREIO_F2A[2181:2181]" net="out[117]" dir="output"/>
	<io name="gfpga_pad_QL_PREIO_F2A[328:328]" net="out[116]" dir="output"/>
	<io name="gfpga_pad_QL_PREIO_F2A[783:783]" net="out[115]" dir="output"/>
	<io name="gfpga_pad_QL_PREIO_F2A[454:454]" net="out[114]" dir="output"/>
	<io name="gfpga_pad_QL_PREIO_F2A[296:296]" net="out[113]" dir="output"/>
	<io name="gfpga_pad_QL_PREIO_F2A[2174:2174]" net="out[112]" dir="output"/>
	<io name="gfpga_pad_QL_PREIO_F2A[663:663]" net="out[111]" dir="output"/>
	<io name="gfpga_pad_QL_PREIO_F2A[705:705]" net="out[110]" dir="output"/>
	<io name="gfpga_pad_QL_PREIO_F2A[662:662]" net="out[109]" dir="output"/>
	<io name="gfpga_pad_QL_PREIO_F2A[295:295]" net="out[108]" dir="output"/>
	<io name="gfpga_pad_QL_PREIO_F2A[407:407]" net="out[107]" dir="output"/>
	<io name="gfpga_pad_QL_PREIO_F2A[312:312]" net="out[106]" dir="output"/>
	<io name="gfpga_pad_QL_PREIO_F2A[634:634]" net="out[105]" dir="output"/>
	<io name="gfpga_pad_QL_PREIO_F2A[2287:2287]" net="out[104]" dir="output"/>
	<io name="gfpga_pad_QL_PREIO_F2A[2144:2144]" net="out[103]" dir="output"/>
	<io name="gfpga_pad_QL_PREIO_F2A[419:419]" net="out[102]" dir="output"/>
	<io name="gfpga_pad_QL_PREIO_F2A[894:894]" net="out[101]" dir="output"/>
	<io name="gfpga_pad_QL_PREIO_F2A[2043:2043]" net="out[100]" dir="output"/>
	<io name="gfpga_pad_QL_PREIO_F2A[2009:2009]" net="out[99]" dir="output"/>
	<io name="gfpga_pad_QL_PREIO_F2A[2098:2098]" net="out[98]" dir="output"/>
	<io name="gfpga_pad_QL_PREIO_F2A[2024:2024]" net="out[97]" dir="output"/>
	<io name="gfpga_pad_QL_PREIO_F2A[2056:2056]" net="out[96]" dir="output"/>
	<io name="gfpga_pad_QL_PREIO_F2A[877:877]" net="out[95]" dir="output"/>
	<io name="gfpga_pad_QL_PREIO_F2A[844:844]" net="out[94]" dir="output"/>
	<io name="gfpga_pad_QL_PREIO_F2A[2107:2107]" net="out[93]" dir="output"/>
	<io name="gfpga_pad_QL_PREIO_F2A[876:876]" net="out[92]" dir="output"/>
	<io name="gfpga_pad_QL_PREIO_F2A[834:834]" net="out[91]" dir="output"/>
	<io name="gfpga_pad_QL_PREIO_F2A[1982:1982]" net="out[90]" dir="output"/>
	<io name="gfpga_pad_QL_PREIO_F2A[1988:1988]" net="out[89]" dir="output"/>
	<io name="gfpga_pad_QL_PREIO_F2A[2145:2145]" net="out[88]" dir="output"/>
	<io name="gfpga_pad_QL_PREIO_F2A[1894:1894]" net="out[87]" dir="output"/>
	<io name="gfpga_pad_QL_PREIO_F2A[953:953]" net="out[86]" dir="output"/>
	<io name="gfpga_pad_QL_PREIO_F2A[1088:1088]" net="out[85]" dir="output"/>
	<io name="gfpga_pad_QL_PREIO_F2A[1051:1051]" net="out[84]" dir="output"/>
	<io name="gfpga_pad_QL_PREIO_F2A[944:944]" net="out[83]" dir="output"/>
	<io name="gfpga_pad_QL_PREIO_F2A[1055:1055]" net="out[82]" dir="output"/>
	<io name="gfpga_pad_QL_PREIO_F2A[901:901]" net="out[81]" dir="output"/>
	<io name="gfpga_pad_QL_PREIO_F2A[1784:1784]" net="out[80]" dir="output"/>
	<io name="gfpga_pad_QL_PREIO_F2A[993:993]" net="out[79]" dir="output"/>
	<io name="gfpga_pad_QL_PREIO_F2A[968:968]" net="out[78]" dir="output"/>
	<io name="gfpga_pad_QL_PREIO_F2A[2061:2061]" net="out[77]" dir="output"/>
	<io name="gfpga_pad_QL_PREIO_F2A[1361:1361]" net="out[76]" dir="output"/>
	<io name="gfpga_pad_QL_PREIO_F2A[1931:1931]" net="out[75]" dir="output"/>
	<io name="gfpga_pad_QL_PREIO_F2A[1050:1050]" net="out[74]" dir="output"/>
	<io name="gfpga_pad_QL_PREIO_F2A[1876:1876]" net="out[73]" dir="output"/>
	<io name="gfpga_pad_QL_PREIO_F2A[1878:1878]" net="out[72]" dir="output"/>
	<io name="gfpga_pad_QL_PREIO_F2A[822:822]" net="out[71]" dir="output"/>
	<io name="gfpga_pad_QL_PREIO_F2A[589:589]" net="out[70]" dir="output"/>
	<io name="gfpga_pad_QL_PREIO_F2A[2178:2178]" net="out[69]" dir="output"/>
	<io name="gfpga_pad_QL_PREIO_F2A[727:727]" net="out[68]" dir="output"/>
	<io name="gfpga_pad_QL_PREIO_F2A[2053:2053]" net="out[67]" dir="output"/>
	<io name="gfpga_pad_QL_PREIO_F2A[853:853]" net="out[66]" dir="output"/>
	<io name="gfpga_pad_QL_PREIO_F2A[604:604]" net="out[65]" dir="output"/>
	<io name="gfpga_pad_QL_PREIO_F2A[582:582]" net="out[64]" dir="output"/>
	<io name="gfpga_pad_QL_PREIO_F2A[644:644]" net="out[63]" dir="output"/>
	<io name="gfpga_pad_QL_PREIO_F2A[594:594]" net="out[62]" dir="output"/>
	<io name="gfpga_pad_QL_PREIO_F2A[167:167]" net="out[61]" dir="output"/>
	<io name="gfpga_pad_QL_PREIO_F2A[2280:2280]" net="out[60]" dir="output"/>
	<io name="gfpga_pad_QL_PREIO_F2A[704:704]" net="out[59]" dir="output"/>
	<io name="gfpga_pad_QL_PREIO_F2A[753:753]" net="out[58]" dir="output"/>
	<io name="gfpga_pad_QL_PREIO_F2A[2065:2065]" net="out[57]" dir="output"/>
	<io name="gfpga_pad_QL_PREIO_F2A[679:679]" net="out[56]" dir="output"/>
	<io name="gfpga_pad_QL_PREIO_F2A[757:757]" net="out[55]" dir="output"/>
	<io name="gfpga_pad_QL_PREIO_F2A[2172:2172]" net="out[54]" dir="output"/>
	<io name="gfpga_pad_QL_PREIO_F2A[2173:2173]" net="out[53]" dir="output"/>
	<io name="gfpga_pad_QL_PREIO_F2A[656:656]" net="out[52]" dir="output"/>
	<io name="gfpga_pad_QL_PREIO_F2A[2184:2184]" net="out[51]" dir="output"/>
	<io name="gfpga_pad_QL_PREIO_F2A[2101:2101]" net="out[50]" dir="output"/>
	<io name="gfpga_pad_QL_PREIO_F2A[752:752]" net="out[49]" dir="output"/>
	<io name="gfpga_pad_QL_PREIO_F2A[2228:2228]" net="out[48]" dir="output"/>
	<io name="gfpga_pad_QL_PREIO_F2A[768:768]" net="out[47]" dir="output"/>
	<io name="gfpga_pad_QL_PREIO_F2A[2140:2140]" net="out[46]" dir="output"/>
	<io name="gfpga_pad_QL_PREIO_F2A[779:779]" net="out[45]" dir="output"/>
	<io name="gfpga_pad_QL_PREIO_F2A[2142:2142]" net="out[44]" dir="output"/>
	<io name="gfpga_pad_QL_PREIO_F2A[2138:2138]" net="out[43]" dir="output"/>
	<io name="gfpga_pad_QL_PREIO_F2A[2206:2206]" net="out[42]" dir="output"/>
	<io name="gfpga_pad_QL_PREIO_F2A[2189:2189]" net="out[41]" dir="output"/>
	<io name="gfpga_pad_QL_PREIO_F2A[424:424]" net="out[40]" dir="output"/>
	<io name="gfpga_pad_QL_PREIO_F2A[244:244]" net="out[39]" dir="output"/>
	<io name="gfpga_pad_QL_PREIO_F2A[225:225]" net="out[38]" dir="output"/>
	<io name="gfpga_pad_QL_PREIO_F2A[271:271]" net="out[37]" dir="output"/>
	<io name="gfpga_pad_QL_PREIO_F2A[2282:2282]" net="out[36]" dir="output"/>
	<io name="gfpga_pad_QL_PREIO_F2A[583:583]" net="out[35]" dir="output"/>
	<io name="gfpga_pad_QL_PREIO_F2A[717:717]" net="out[34]" dir="output"/>
	<io name="gfpga_pad_QL_PREIO_F2A[265:265]" net="out[33]" dir="output"/>
	<io name="gfpga_pad_QL_PREIO_F2A[298:298]" net="out[32]" dir="output"/>
	<io name="gfpga_pad_QL_PREIO_F2A[2180:2180]" net="out[31]" dir="output"/>
	<io name="gfpga_pad_QL_PREIO_F2A[226:226]" net="out[30]" dir="output"/>
	<io name="gfpga_pad_QL_PREIO_F2A[670:670]" net="out[29]" dir="output"/>
	<io name="gfpga_pad_QL_PREIO_F2A[356:356]" net="out[28]" dir="output"/>
	<io name="gfpga_pad_QL_PREIO_F2A[2169:2169]" net="out[27]" dir="output"/>
	<io name="gfpga_pad_QL_PREIO_F2A[330:330]" net="out[26]" dir="output"/>
	<io name="gfpga_pad_QL_PREIO_F2A[425:425]" net="out[25]" dir="output"/>
	<io name="gfpga_pad_QL_PREIO_F2A[274:274]" net="out[24]" dir="output"/>
	<io name="gfpga_pad_QL_PREIO_F2A[2133:2133]" net="out[23]" dir="output"/>
	<io name="gfpga_pad_QL_PREIO_F2A[2063:2063]" net="out[22]" dir="output"/>
	<io name="gfpga_pad_QL_PREIO_F2A[1833:1833]" net="out[21]" dir="output"/>
	<io name="gfpga_pad_QL_PREIO_F2A[2075:2075]" net="out[20]" dir="output"/>
	<io name="gfpga_pad_QL_PREIO_F2A[1815:1815]" net="out[19]" dir="output"/>
	<io name="gfpga_pad_QL_PREIO_F2A[1966:1966]" net="out[18]" dir="output"/>
	<io name="gfpga_pad_QL_PREIO_F2A[2104:2104]" net="out[17]" dir="output"/>
	<io name="gfpga_pad_QL_PREIO_F2A[1925:1925]" net="out[16]" dir="output"/>
	<io name="gfpga_pad_QL_PREIO_F2A[1914:1914]" net="out[15]" dir="output"/>
	<io name="gfpga_pad_QL_PREIO_F2A[1890:1890]" net="out[14]" dir="output"/>
	<io name="gfpga_pad_QL_PREIO_F2A[1976:1976]" net="out[13]" dir="output"/>
	<io name="gfpga_pad_QL_PREIO_F2A[1961:1961]" net="out[12]" dir="output"/>
	<io name="gfpga_pad_QL_PREIO_F2A[2141:2141]" net="out[11]" dir="output"/>
	<io name="gfpga_pad_QL_PREIO_F2A[1892:1892]" net="out[10]" dir="output"/>
	<io name="gfpga_pad_QL_PREIO_F2A[1743:1743]" net="out[9]" dir="output"/>
	<io name="gfpga_pad_QL_PREIO_F2A[1887:1887]" net="out[8]" dir="output"/>
	<io name="gfpga_pad_QL_PREIO_F2A[1904:1904]" net="out[7]" dir="output"/>
	<io name="gfpga_pad_QL_PREIO_F2A[1818:1818]" net="out[6]" dir="output"/>
	<io name="gfpga_pad_QL_PREIO_F2A[1915:1915]" net="out[5]" dir="output"/>
	<io name="gfpga_pad_QL_PREIO_F2A[2027:2027]" net="out[4]" dir="output"/>
	<io name="gfpga_pad_QL_PREIO_F2A[2045:2045]" net="out[3]" dir="output"/>
	<io name="gfpga_pad_QL_PREIO_F2A[1882:1882]" net="out[2]" dir="output"/>
	<io name="gfpga_pad_QL_PREIO_F2A[2058:2058]" net="out[1]" dir="output"/>
	<io name="gfpga_pad_QL_PREIO_F2A[174:174]" net="out[0]" dir="output"/>
</io_mapping>
