[
    {
        "": {
            "header": [
                "Logic",
                "Used",
                "Available",
                "%"
            ],
            "data": [
                [
                    "CLB",
                    "0",
                    "2184",
                    "0"
                ],
                [
                    "       LUTs",
                    "68",
                    "17472",
                    "0"
                ],
                [
                    "       Registers",
                    "4",
                    "34944",
                    "0"
                ],
                [
                    "              Flip Flop",
                    "4",
                    "34944",
                    "0"
                ],
                [
                    "       Adder Carry",
                    "32",
                    "17472",
                    "0"
                ]
            ]
        }
    },
    {
        "": {
            "header": [
                "Block RAM",
                "Used",
                "Available",
                "%"
            ],
            "data": [
                [
                    "BRAM",
                    "1",
                    "56",
                    "1"
                ],
                [
                    "       18k",
                    "0",
                    "112",
                    "0"
                ],
                [
                    "       36k",
                    "1",
                    "56",
                    "1"
                ]
            ]
        }
    },
    {
        "": {
            "header": [
                "DSP",
                "Used",
                "Available",
                "%"
            ],
            "data": [
                [
                    "DSP Block",
                    "0",
                    "56",
                    "0"
                ],
                [
                    "       9x10",
                    "0",
                    "56",
                    "0"
                ],
                [
                    "       18x20",
                    "0",
                    "112",
                    "0"
                ]
            ]
        }
    },
    {
        "": {
            "header": [
                "I/O",
                "Used",
                "Available",
                "%"
            ],
            "data": [
                [
                    "I/O",
                    "0",
                    "240",
                    "0"
                ],
                [
                    "       Inputs",
                    "0",
                    "240",
                    "0"
                ],
                [
                    "       Outputs",
                    "0",
                    "240",
                    "0"
                ]
            ]
        }
    },
    {
        "": {
            "header": [
                "Clock",
                "Used"
            ],
            "data": [
                [
                    "Clock",
                    "0"
                ]
            ]
        }
    }
]