[
      {
          "ports": [
              {
                  "direction": "Input",
                  "name": "clk",
                  "range": {
                      "lsb": 0,
                      "msb": 0
                  },
                  "type": "LOGIC"
              },
              {
                  "direction": "Input",
                  "name": "rst",
                  "range": {
                      "lsb": 0,
                      "msb": 0
                  },
                  "type": "LOGIC"
              },
              {
                  "direction": "Input",
                  "name": "dIn",
                  "range": {
                      "lsb": 0,
                      "msb": 0
                  },
                  "type": "LOGIC"
              },
              {
                  "direction": "Input",
                  "name": "dInValid",
                  "range": {
                      "lsb": 0,
                      "msb": 0
                  },
                  "type": "LOGIC"
              },
              {
                  "direction": "Output",
                  "name": "nextDin",
                  "range": {
                      "lsb": 0,
                      "msb": 0
                  },
                  "type": "LOGIC"
              },
              {
                  "direction": "Input",
                  "name": "start",
                  "range": {
                      "lsb": 0,
                      "msb": 0
                  },
                  "type": "LOGIC"
              },
              {
                  "direction": "Output",
                  "name": "dOut",
                  "range": {
                      "lsb": 0,
                      "msb": 7
                  },
                  "type": "LOGIC"
              },
              {
                  "direction": "Output",
                  "name": "dOutValid",
                  "range": {
                      "lsb": 0,
                      "msb": 0
                  },
                  "type": "LOGIC"
              },
              {
                  "direction": "Input",
                  "name": "nextDout",
                  "range": {
                      "lsb": 0,
                      "msb": 0
                  },
                  "type": "LOGIC"
              },
              {
                  "direction": "Input",
                  "name": "inputDiscardCnt",
                  "range": {
                      "lsb": 0,
                      "msb": 0
                  },
                  "type": "LOGIC"
              },
              {
                  "direction": "Input",
                  "name": "inputXRes",
                  "range": {
                      "lsb": 0,
                      "msb": 0
                  },
                  "type": "LOGIC"
              },
              {
                  "direction": "Input",
                  "name": "inputYRes",
                  "range": {
                      "lsb": 0,
                      "msb": 0
                  },
                  "type": "LOGIC"
              },
              {
                  "direction": "Input",
                  "name": "outputXRes",
                  "range": {
                      "lsb": 0,
                      "msb": 0
                  },
                  "type": "LOGIC"
              },
              {
                  "direction": "Input",
                  "name": "outputYRes",
                  "range": {
                      "lsb": 0,
                      "msb": 0
                  },
                  "type": "LOGIC"
              },
              {
                  "direction": "Input",
                  "name": "xScale",
                  "range": {
                      "lsb": 0,
                      "msb": 0
                  },
                  "type": "LOGIC"
              },
              {
                  "direction": "Input",
                  "name": "yScale",
                  "range": {
                      "lsb": 0,
                      "msb": 0
                  },
                  "type": "LOGIC"
              },
              {
                  "direction": "Input",
                  "name": "leftOffset",
                  "range": {
                      "lsb": 0,
                      "msb": 0
                  },
                  "type": "LOGIC"
              },
              {
                  "direction": "Input",
                  "name": "topFracOffset",
                  "range": {
                      "lsb": 0,
                      "msb": 0
                  },
                  "type": "LOGIC"
              },
              {
                  "direction": "Input",
                  "name": "nearestNeighbor",
                  "range": {
                      "lsb": 0,
                      "msb": 0
                  },
                  "type": "LOGIC"
              }
          ],
          "topModule": "streamScaler_sr_top"
      }
]
