{
    "strategy": "delay",
    "total_runtime": 948178,
    "synthesis_runtime": 40186,
    "packing_runtime": 41380,
    "placement_runtime": 260325,
    "routing_runtime": 120271,
    "time_analysis_runtime": 36628,
    "bitstream_runtime": 448283,
    "reg_id": "23",
    "device": "GEMINI_COMPACT_104x68",
    "target device": "GEMINI_COMPACT_104x68",
    "version": "2023.10",
    "git_hash": "4d0c7ee",
    "built": "0.8.44",
    "built_type": "Engineering",
    "status": "Pass",
    "error_msg": null,
    "post_synth_sim_status": null,
    "post_route_sim_status": null,
    "bitstream_sim_status": null,
    "failure_type": null,
    "fmax_clock1": 276.514,
    "fmax_clock2": null,
    "fmax_clock3": null,
    "fmax_clock4": null,
    "fmax_clock5": null,
    "fmax_clock6": null,
    "wns_clock1": -3.61645,
    "wns_clock2": null,
    "wns_clock3": null,
    "wns_clock4": null,
    "wns_clock5": null,
    "wns_clock6": null,
    "tns": -1704.77,
    "fmax_geomean": 276.514,
    "registers": 488,
    "total_luts": 754,
    "brams": null,
    "dsp": 3,
    "Adder_Carry": null,
    "CLB": 66,
    "LUT_CLB_ratio": 0.0,
    "CLB_percentage_used": 1.1627906976744187,
    "FLE_Percentage_used": 1.1539816772374911,
    "Wirelength_Percentage_used": 0.6919427191166322,
    "logic_level_clock1": 0,
    "logic_level_clock2": null,
    "logic_level_clock3": null,
    "logic_level_clock4": null,
    "logic_level_clock5": null,
    "logic_level_clock6": null,
    "total_power": null,
    "dynamic_power": null,
    "static_power": null,
    "target_freq_clock1": null,
    "target_freq_clock2": null,
    "target_freq_clock3": null,
    "target_freq_clock4": null,
    "target_freq_clock5": null,
    "target_freq_clock6": null
}