{
    "strategy": "delay",
    "total_runtime": 1002973,
    "synthesis_runtime": 8292,
    "packing_runtime": 37117,
    "placement_runtime": 275180,
    "routing_runtime": 127683,
    "time_analysis_runtime": 38205,
    "bitstream_runtime": 499567,
    "reg_id": "23",
    "device": "GEMINI_COMPACT_104x68",
    "target device": "GEMINI_COMPACT_104x68",
    "version": "2023.10",
    "git_hash": "dc7fe85",
    "built": "0.8.47",
    "built_type": "Engineering",
    "status": "Pass",
    "error_msg": null,
    "post_synth_sim_status": null,
    "post_route_sim_status": null,
    "bitstream_sim_status": null,
    "failure_type": null,
    "fmax_clock1": 423.107,
    "fmax_clock2": null,
    "fmax_clock3": null,
    "fmax_clock4": null,
    "fmax_clock5": null,
    "fmax_clock6": null,
    "wns_clock1": -2.36347,
    "wns_clock2": null,
    "wns_clock3": null,
    "wns_clock4": null,
    "wns_clock5": null,
    "wns_clock6": null,
    "tns": -15.5156,
    "fmax_geomean": 423.107,
    "registers": 5,
    "total_luts": 6,
    "brams": null,
    "dsp": null,
    "Adder_Carry": null,
    "CLB": 1,
    "LUT_CLB_ratio": 0.0,
    "CLB_percentage_used": 0.017618040873854827,
    "FLE_Percentage_used": 0.011011275546159266,
    "Wirelength_Percentage_used": 0.004744651483781919,
    "logic_level_clock1": 0,
    "logic_level_clock2": null,
    "logic_level_clock3": null,
    "logic_level_clock4": null,
    "logic_level_clock5": null,
    "logic_level_clock6": null,
    "total_power": null,
    "dynamic_power": null,
    "static_power": null,
    "target_freq_clock1": null,
    "target_freq_clock2": null,
    "target_freq_clock3": null,
    "target_freq_clock4": null,
    "target_freq_clock5": null,
    "target_freq_clock6": null
}